{
    "attributes": {
        "description": "",
        "kibanaSavedObjectMeta": {
            "searchSourceJSON": "{\"index\":\"confluence\",\"query\":{\"query_string\":{\"query\":\"*\",\"analyze_wildcard\":true}},\"filter\":[]}"
        },
        "title": "confluence_top_editors",
        "uiStateJSON": "{\"vis\":{\"params\":{\"sort\":{\"columnIndex\":null,\"direction\":null}}}}",
        "version": 1,
        "visState": "{\"title\":\"confluence_top_editors\",\"type\":\"table\",\"params\":{\"perPage\":10,\"showPartialRows\":false,\"showMeticsAtAllLevels\":false,\"sort\":{\"columnIndex\":null,\"direction\":null},\"showTotal\":false,\"totalFunc\":\"sum\"},\"aggs\":[{\"id\":\"2\",\"enabled\":true,\"type\":\"terms\",\"schema\":\"bucket\",\"params\":{\"field\":\"author_name\",\"size\":200,\"order\":\"desc\",\"orderBy\":\"3\",\"customLabel\":\"Editor\"}},{\"id\":\"3\",\"enabled\":true,\"type\":\"sum\",\"schema\":\"metric\",\"params\":{\"field\":\"is_page\",\"customLabel\":\"Page Edits\"}},{\"id\":\"1\",\"enabled\":true,\"type\":\"sum\",\"schema\":\"metric\",\"params\":{\"field\":\"is_new_page\",\"customLabel\":\"New Pages\"}},{\"id\":\"4\",\"enabled\":true,\"type\":\"sum\",\"schema\":\"metric\",\"params\":{\"field\":\"is_comment\",\"customLabel\":\"Comments\"}},{\"id\":\"5\",\"enabled\":true,\"type\":\"sum\",\"schema\":\"metric\",\"params\":{\"field\":\"is_blogpost\",\"customLabel\":\"Blog Posts\"}},{\"id\":\"6\",\"enabled\":true,\"type\":\"sum\",\"schema\":\"metric\",\"params\":{\"field\":\"is_attachment\",\"customLabel\":\"Attachments\"}},{\"id\":\"7\",\"enabled\":true,\"type\":\"max\",\"schema\":\"metric\",\"params\":{\"field\":\"grimoire_creation_date\",\"customLabel\":\"Last Action Date\"}}],\"listeners\":{}}"
    },
    "id": "confluence_top_editors",
    "migrationVersion": {
        "visualization": "6.7.2"
    },
    "type": "visualization",
    "version": "WzExODYsMV0="
}