{
    "attributes": {
        "description": "",
        "kibanaSavedObjectMeta": {
            "searchSourceJSON": "{\"index\":\"jira\",\"query\":{\"query\":{\"query_string\":{\"query\":\"*\",\"analyze_wildcard\":true,\"default_field\":\"*\"}},\"language\":\"lucene\"},\"filter\":[]}"
        },
        "title": "jira_issues_organizations_submitters",
        "uiStateJSON": "{}",
        "version": 1,
        "visState": "{\"title\":\"jira_issues_organizations_submitters\",\"type\":\"pie\",\"params\":{\"shareYAxis\":true,\"addTooltip\":true,\"addLegend\":true,\"isDonut\":true,\"legendPosition\":\"right\",\"type\":\"pie\",\"labels\":{\"show\":false,\"values\":true,\"last_level\":true,\"truncate\":100}},\"aggs\":[{\"id\":\"1\",\"enabled\":true,\"type\":\"count\",\"schema\":\"metric\",\"params\":{\"customLabel\":\"Issues\"}},{\"id\":\"2\",\"enabled\":true,\"type\":\"terms\",\"schema\":\"segment\",\"params\":{\"field\":\"creator_org_name\",\"size\":1000,\"order\":\"desc\",\"orderBy\":\"1\",\"customLabel\":\"Submitters\"}}]}"
    },
    "id": "dcb31b80-4b16-11e9-b68b-31a1aa44b23a",
    "migrationVersion": {
        "visualization": "6.7.2"
    },
    "type": "visualization",
    "version": "WzU3OSwxXQ=="
}