{
    "attributes": {
        "description": "",
        "kibanaSavedObjectMeta": {
            "searchSourceJSON": "{}"
        },
        "title": "gitlab_orgs_projects_options",
        "uiStateJSON": "{}",
        "version": 1,
        "visState": "{\"title\":\"gitlab_orgs_projects_options\",\"type\":\"input_control_vis\",\"params\":{\"controls\":[{\"id\":\"1543836411285\",\"indexPattern\":\"7c2496c0-b013-11e8-8771-a349686d998a\",\"fieldName\":\"author_org_name\",\"label\":\"Organizations\",\"type\":\"list\",\"options\":{\"type\":\"terms\",\"multiselect\":true,\"size\":5,\"order\":\"desc\"}},{\"id\":\"1543836458831\",\"indexPattern\":\"7c2496c0-b013-11e8-8771-a349686d998a\",\"fieldName\":\"project\",\"label\":\"Projects\",\"type\":\"list\",\"options\":{\"type\":\"terms\",\"multiselect\":true,\"size\":5,\"order\":\"desc\"}}],\"updateFiltersOnChange\":false},\"aggs\":[]}"
    },
    "id": "8d2c9a40-f6ee-11e8-8aac-ef7fd4d8cbad",
    "migrationVersion": {
        "visualization": "6.7.2"
    },
    "type": "visualization",
    "version": "WzExNjgsMV0="
}