{
    "attributes": {
        "description": "",
        "kibanaSavedObjectMeta": {
            "searchSourceJSON": "{\"index\":\"google-hits\",\"query\":{\"query\":{\"query_string\":{\"query\":\"*\",\"analyze_wildcard\":true,\"default_field\":\"*\"}},\"language\":\"lucene\"},\"filter\":[]}"
        },
        "title": "googlehits_avg_hits_evolutionary",
        "uiStateJSON": "{\"vis\":{\"legendOpen\":false}}",
        "version": 1,
        "visState": "{\"title\":\"googlehits_avg_hits_evolutionary\",\"type\":\"histogram\",\"params\":{\"shareYAxis\":true,\"addTooltip\":true,\"addLegend\":true,\"scale\":\"linear\",\"mode\":\"stacked\",\"times\":[],\"addTimeMarker\":false,\"defaultYExtents\":false,\"setYExtents\":false,\"yAxis\":{},\"type\":\"histogram\",\"grid\":{\"categoryLines\":false,\"style\":{\"color\":\"#eee\"}},\"categoryAxes\":[{\"id\":\"CategoryAxis-1\",\"type\":\"category\",\"position\":\"bottom\",\"show\":true,\"style\":{},\"scale\":{\"type\":\"linear\"},\"labels\":{\"show\":true,\"truncate\":100},\"title\":{}}],\"valueAxes\":[{\"id\":\"ValueAxis-1\",\"name\":\"LeftAxis-1\",\"type\":\"value\",\"position\":\"left\",\"show\":true,\"style\":{},\"scale\":{\"type\":\"linear\",\"mode\":\"normal\",\"setYExtents\":false,\"defaultYExtents\":false},\"labels\":{\"show\":true,\"rotate\":0,\"filter\":false,\"truncate\":100},\"title\":{\"text\":\"Hits (average)\"}}],\"seriesParams\":[{\"show\":\"true\",\"type\":\"histogram\",\"mode\":\"stacked\",\"data\":{\"label\":\"Hits (average)\",\"id\":\"1\"},\"valueAxis\":\"ValueAxis-1\"}],\"legendPosition\":\"right\"},\"aggs\":[{\"id\":\"1\",\"enabled\":true,\"type\":\"avg\",\"schema\":\"metric\",\"params\":{\"field\":\"hits\",\"customLabel\":\"Hits (average)\"}},{\"id\":\"2\",\"enabled\":true,\"type\":\"date_histogram\",\"schema\":\"segment\",\"params\":{\"field\":\"grimoire_creation_date\",\"interval\":\"auto\",\"customInterval\":\"2h\",\"min_doc_count\":1,\"extended_bounds\":{},\"customLabel\":\"Time\"}},{\"id\":\"3\",\"enabled\":true,\"type\":\"terms\",\"schema\":\"split\",\"params\":{\"field\":\"keywords\",\"size\":7,\"order\":\"asc\",\"orderBy\":\"1\",\"customLabel\":\"_\",\"row\":true}}]}"
    },
    "id": "googlehits_avg_hits_evolutionary",
    "migrationVersion": {
        "visualization": "6.7.2"
    },
    "type": "visualization",
    "version": "WzQ4MiwxXQ=="
}