{
    "dashboard": {
        "id": "Meetup-Locations",
        "value": {
            "description": "Meetup Locations panel by Bitergia",
            "hits": 0,
            "kibanaSavedObjectMeta": {
                "searchSourceJSON": "{\"filter\":[{\"meta\":{\"index\":\"meetup\",\"negate\":true,\"disabled\":false,\"alias\":\"Bots\",\"type\":\"phrase\",\"key\":\"author_bot\",\"value\":\"true\",\"params\":{\"query\":true,\"type\":\"phrase\"}},\"query\":{\"match\":{\"author_bot\":{\"query\":true,\"type\":\"phrase\"}}},\"$state\":{\"store\":\"appState\"}}],\"version\":true,\"query\":{\"language\":\"lucene\",\"query\":{\"query_string\":{\"analyze_wildcard\":true,\"default_field\":\"*\",\"query\":\"*\"}}},\"highlightAll\":true}"
            },
            "optionsJSON": "{\"darkTheme\":false,\"useMargins\":true}",
            "panelsJSON": "[{\"gridData\":{\"h\":5,\"i\":\"3\",\"w\":5,\"x\":0,\"y\":0},\"id\":\"meetup_groups_map\",\"panelIndex\":\"3\",\"title\":\"Groups\",\"type\":\"visualization\",\"version\":\"6.1.0-3\"},{\"gridData\":{\"h\":6,\"i\":\"6\",\"w\":5,\"x\":0,\"y\":5},\"id\":\"meetup_organizers\",\"panelIndex\":\"6\",\"title\":\"Organizers\",\"type\":\"visualization\",\"version\":\"6.1.0-3\"},{\"gridData\":{\"h\":6,\"i\":\"7\",\"w\":7,\"x\":5,\"y\":5},\"id\":\"meetup_groups_large\",\"panelIndex\":\"7\",\"title\":\"Meetup Groups\",\"type\":\"visualization\",\"version\":\"6.1.0-3\"},{\"gridData\":{\"h\":5,\"i\":\"8\",\"w\":4,\"x\":5,\"y\":0},\"id\":\"meetup_organizations\",\"panelIndex\":\"8\",\"title\":\"Organizations\",\"type\":\"visualization\",\"version\":\"6.1.0-3\"},{\"gridData\":{\"h\":5,\"i\":\"9\",\"w\":3,\"x\":9,\"y\":0},\"id\":\"meetup_projects\",\"panelIndex\":\"9\",\"title\":\"Projects\",\"type\":\"visualization\",\"version\":\"6.1.0-3\"}]",
            "release_date": "2019-07-02T14:10:14.029007",
            "timeRestore": false,
            "title": "Meetup Locations",
            "uiStateJSON": "{\"P-3\":{\"mapCenter\":[11.178401873711785,0],\"mapZoom\":1,\"title\":\"Groups\"},\"P-6\":{\"title\":\"Organizers\",\"vis\":{\"params\":{\"config\":{\"searchKeyword\":\"\"},\"sort\":{\"columnIndex\":null,\"direction\":null}}}},\"P-7\":{\"title\":\"Meetup Groups\",\"vis\":{\"params\":{\"config\":{\"searchKeyword\":\"\"},\"sort\":{\"columnIndex\":null,\"direction\":null}}}},\"P-8\":{\"title\":\"Organizations\",\"vis\":{\"params\":{\"config\":{\"searchKeyword\":\"\"},\"sort\":{\"columnIndex\":null,\"direction\":null}}}},\"P-9\":{\"title\":\"Projects\",\"vis\":{\"params\":{\"config\":{\"searchKeyword\":\"\"},\"sort\":{\"columnIndex\":null,\"direction\":null}}}}}",
            "version": 1
        }
    },
    "searches": [
        {
            "id": "Meetup-Search:_type_meetup",
            "value": {
                "columns": [
                    "_source"
                ],
                "description": "",
                "hits": 0,
                "kibanaSavedObjectMeta": {
                    "searchSourceJSON": "{\"index\":\"meetup\",\"filter\":[],\"highlight\":{\"pre_tags\":[\"@kibana-highlighted-field@\"],\"post_tags\":[\"@/kibana-highlighted-field@\"],\"fields\":{\"*\":{}},\"require_field_match\":false,\"fragment_size\":2147483647},\"query\":{\"query_string\":{\"query\":\"type:meetup\",\"analyze_wildcard\":true}}}"
                },
                "sort": [
                    "grimoire_creation_date",
                    "desc"
                ],
                "title": "Meetup Search:_type_meetup",
                "version": 1
            }
        }
    ],
    "visualizations": [
        {
            "id": "meetup_groups_map",
            "value": {
                "description": "",
                "kibanaSavedObjectMeta": {
                    "searchSourceJSON": "{\"filter\":[]}"
                },
                "savedSearchId": "Meetup-Search:_type_meetup",
                "title": "meetup_groups_map",
                "uiStateJSON": "{\"mapCenter\":[48.86471476180277,2.5048828125],\"mapZoom\":5}",
                "version": 1,
                "visState": "{\"title\":\"meetup_groups_map\",\"type\":\"tile_map\",\"params\":{\"mapType\":\"Shaded Circle Markers\",\"isDesaturated\":true,\"addTooltip\":true,\"heatMaxZoom\":16,\"heatMinOpacity\":0.1,\"heatRadius\":25,\"heatBlur\":15,\"heatNormalizeData\":true,\"wms\":{\"enabled\":false,\"url\":\"https://basemap.nationalmap.gov/arcgis/services/USGSTopo/MapServer/WMSServer\",\"options\":{\"version\":\"1.3.0\",\"layers\":\"0\",\"format\":\"image/png\",\"transparent\":true,\"attribution\":\"Maps provided by USGS\",\"styles\":\"\"}},\"legendPosition\":\"bottomright\",\"mapZoom\":2,\"mapCenter\":[15,5]},\"aggs\":[{\"id\":\"1\",\"enabled\":true,\"type\":\"count\",\"schema\":\"metric\",\"params\":{\"customLabel\":\"# Groups\"}},{\"id\":\"2\",\"enabled\":true,\"type\":\"geohash_grid\",\"schema\":\"segment\",\"params\":{\"field\":\"group_geolocation\",\"autoPrecision\":true,\"mapZoom\":2,\"mapCenter\":[15.114552871944102,4.21875],\"precision\":2}}],\"listeners\":{}}"
            }
        },
        {
            "id": "meetup_organizers",
            "value": {
                "description": "",
                "kibanaSavedObjectMeta": {
                    "searchSourceJSON": "{\"filter\":[],\"query\":{\"query\":\"\",\"language\":\"lucene\"}}"
                },
                "savedSearchId": "Meetup-Search:_type_meetup",
                "title": "meetup_organizers",
                "uiStateJSON": "{\"vis\":{\"params\":{\"sort\":{\"columnIndex\":null,\"direction\":null}}}}",
                "version": 1,
                "visState": "{\"title\":\"meetup_organizers\",\"type\":\"table\",\"params\":{\"perPage\":10,\"showPartialRows\":false,\"showMeticsAtAllLevels\":false,\"sort\":{\"columnIndex\":null,\"direction\":null},\"showTotal\":false,\"totalFunc\":\"sum\"},\"aggs\":[{\"id\":\"1\",\"enabled\":true,\"type\":\"count\",\"schema\":\"metric\",\"params\":{\"customLabel\":\"# Meetups\"}},{\"id\":\"2\",\"enabled\":true,\"type\":\"terms\",\"schema\":\"bucket\",\"params\":{\"field\":\"author_name\",\"size\":50,\"order\":\"desc\",\"orderBy\":\"1\",\"customLabel\":\"Organizer\"}}]}"
            }
        },
        {
            "id": "meetup_groups_large",
            "value": {
                "description": "",
                "kibanaSavedObjectMeta": {
                    "searchSourceJSON": "{\"filter\":[]}"
                },
                "savedSearchId": "Meetup-Search:_type_meetup",
                "title": "meetup_groups_large",
                "uiStateJSON": "{\"vis\":{\"params\":{\"sort\":{\"columnIndex\":null,\"direction\":null}}}}",
                "version": 1,
                "visState": "{\"title\":\"meetup_groups_large\",\"type\":\"table\",\"params\":{\"perPage\":10,\"showMeticsAtAllLevels\":false,\"showPartialRows\":false,\"sort\":{\"columnIndex\":null,\"direction\":null},\"showTotal\":false,\"totalFunc\":\"sum\"},\"aggs\":[{\"id\":\"7\",\"enabled\":true,\"type\":\"cardinality\",\"schema\":\"metric\",\"params\":{\"field\":\"event_url\",\"customLabel\":\"Meetings\"}},{\"id\":\"4\",\"enabled\":true,\"type\":\"median\",\"schema\":\"metric\",\"params\":{\"field\":\"num_rsvps\",\"percents\":[50],\"customLabel\":\"Median RSVPs\"}},{\"id\":\"6\",\"enabled\":true,\"type\":\"terms\",\"schema\":\"bucket\",\"params\":{\"field\":\"group_name\",\"size\":50,\"order\":\"desc\",\"orderBy\":\"7\",\"customLabel\":\"Group\"}},{\"id\":\"8\",\"enabled\":true,\"type\":\"min\",\"schema\":\"metric\",\"params\":{\"field\":\"time_date\",\"customLabel\":\"First Meeting\"}},{\"id\":\"9\",\"enabled\":true,\"type\":\"max\",\"schema\":\"metric\",\"params\":{\"field\":\"time_date\",\"customLabel\":\"Most Recent Meeting\"}}],\"listeners\":{}}"
            }
        },
        {
            "id": "meetup_organizations",
            "value": {
                "description": "",
                "kibanaSavedObjectMeta": {
                    "searchSourceJSON": "{\"index\":\"meetup\",\"query\":{\"query_string\":{\"query\":\"*\",\"analyze_wildcard\":true}},\"filter\":[]}"
                },
                "title": "meetup_organizations",
                "uiStateJSON": "{\"vis\":{\"params\":{\"sort\":{\"columnIndex\":null,\"direction\":null}}}}",
                "version": 1,
                "visState": "{\"title\":\"meetup_organizations\",\"type\":\"table\",\"params\":{\"perPage\":5,\"showPartialRows\":false,\"showMeticsAtAllLevels\":false,\"sort\":{\"columnIndex\":null,\"direction\":null},\"showTotal\":false,\"totalFunc\":\"sum\"},\"aggs\":[{\"id\":\"1\",\"enabled\":true,\"type\":\"sum\",\"schema\":\"metric\",\"params\":{\"field\":\"is_meetup_meetup\",\"customLabel\":\"Meetups\"}},{\"id\":\"2\",\"enabled\":true,\"type\":\"terms\",\"schema\":\"bucket\",\"params\":{\"field\":\"author_org_name\",\"size\":500,\"order\":\"desc\",\"orderBy\":\"1\",\"customLabel\":\"Organization\"}},{\"id\":\"3\",\"enabled\":true,\"type\":\"sum\",\"schema\":\"metric\",\"params\":{\"field\":\"is_meetup_rsvp\",\"customLabel\":\"RSVPS\"}},{\"id\":\"4\",\"enabled\":true,\"type\":\"sum\",\"schema\":\"metric\",\"params\":{\"field\":\"is_meetup_comment\",\"customLabel\":\"Comments\"}},{\"id\":\"5\",\"enabled\":true,\"type\":\"cardinality\",\"schema\":\"metric\",\"params\":{\"field\":\"author_uuid\",\"customLabel\":\"People\"}}],\"listeners\":{}}"
            }
        },
        {
            "id": "meetup_projects",
            "value": {
                "description": "",
                "kibanaSavedObjectMeta": {
                    "searchSourceJSON": "{\"index\":\"meetup\",\"query\":{\"query_string\":{\"query\":\"*\",\"analyze_wildcard\":true}},\"filter\":[]}"
                },
                "title": "meetup_projects",
                "uiStateJSON": "{\"vis\":{\"params\":{\"sort\":{\"columnIndex\":null,\"direction\":null}}}}",
                "version": 1,
                "visState": "{\"title\":\"meetup_projects\",\"type\":\"table\",\"params\":{\"perPage\":5,\"showPartialRows\":false,\"showMeticsAtAllLevels\":false,\"sort\":{\"columnIndex\":null,\"direction\":null},\"showTotal\":false,\"totalFunc\":\"sum\"},\"aggs\":[{\"id\":\"1\",\"enabled\":true,\"type\":\"sum\",\"schema\":\"metric\",\"params\":{\"field\":\"is_meetup_meetup\",\"customLabel\":\"Meetups\"}},{\"id\":\"3\",\"enabled\":true,\"type\":\"sum\",\"schema\":\"metric\",\"params\":{\"field\":\"is_meetup_rsvp\",\"customLabel\":\"RSVPS\"}},{\"id\":\"5\",\"enabled\":true,\"type\":\"sum\",\"schema\":\"metric\",\"params\":{\"field\":\"is_meetup_comment\",\"customLabel\":\"Comments\"}},{\"id\":\"4\",\"enabled\":true,\"type\":\"cardinality\",\"schema\":\"metric\",\"params\":{\"field\":\"author_uuid\",\"customLabel\":\"People\"}},{\"id\":\"2\",\"enabled\":true,\"type\":\"terms\",\"schema\":\"bucket\",\"params\":{\"field\":\"project\",\"size\":500,\"order\":\"desc\",\"orderBy\":\"1\",\"customLabel\":\"Project\"}}],\"listeners\":{}}"
            }
        }
    ]
}