{
    "index_patterns": [
        {
            "id": "jira_resolution_date",
            "value": {
                "fieldFormatMap": "{\"resolution_date\":{\"id\":\"date\",\"params\":{\"pattern\":\"MMM Do YYYY, HH:mm:ss\"}},\"author_uuid\":{\"id\":\"url\",\"params\":{\"urlTemplate\":\"/identities/hatstall/{{rawValue}}\",\"labelTemplate\":\"Go to Hatstall\"}},\"painless_delay\":{}}",
                "fields": "[{\"name\":\"_id\",\"type\":\"string\",\"count\":0,\"scripted\":false,\"searchable\":true,\"aggregatable\":true,\"readFromDocValues\":false},{\"name\":\"_index\",\"type\":\"string\",\"count\":0,\"scripted\":false,\"searchable\":true,\"aggregatable\":true,\"readFromDocValues\":false},{\"name\":\"_score\",\"type\":\"number\",\"count\":0,\"scripted\":false,\"searchable\":false,\"aggregatable\":false,\"readFromDocValues\":false},{\"name\":\"_source\",\"type\":\"_source\",\"count\":0,\"scripted\":false,\"searchable\":false,\"aggregatable\":false,\"readFromDocValues\":false},{\"name\":\"_type\",\"type\":\"string\",\"count\":0,\"scripted\":false,\"searchable\":true,\"aggregatable\":true,\"readFromDocValues\":false},{\"name\":\"assignee\",\"type\":\"string\",\"count\":0,\"scripted\":false,\"searchable\":true,\"aggregatable\":true,\"readFromDocValues\":true},{\"name\":\"assignee_bot\",\"type\":\"boolean\",\"count\":0,\"scripted\":false,\"searchable\":true,\"aggregatable\":true,\"readFromDocValues\":true},{\"name\":\"assignee_domain\",\"type\":\"string\",\"count\":0,\"scripted\":false,\"searchable\":true,\"aggregatable\":true,\"readFromDocValues\":true},{\"name\":\"assignee_gender\",\"type\":\"string\",\"count\":0,\"scripted\":false,\"searchable\":true,\"aggregatable\":true,\"readFromDocValues\":true},{\"name\":\"assignee_gender_acc\",\"type\":\"number\",\"count\":0,\"scripted\":false,\"searchable\":true,\"aggregatable\":true,\"readFromDocValues\":true},{\"name\":\"assignee_id\",\"type\":\"string\",\"count\":0,\"scripted\":false,\"searchable\":true,\"aggregatable\":true,\"readFromDocValues\":true},{\"name\":\"assignee_name\",\"type\":\"string\",\"count\":0,\"scripted\":false,\"searchable\":true,\"aggregatable\":true,\"readFromDocValues\":true},{\"name\":\"assignee_org_name\",\"type\":\"string\",\"count\":0,\"scripted\":false,\"searchable\":true,\"aggregatable\":true,\"readFromDocValues\":true},{\"name\":\"assignee_tz\",\"type\":\"string\",\"count\":0,\"scripted\":false,\"searchable\":true,\"aggregatable\":true,\"readFromDocValues\":true},{\"name\":\"assignee_user_name\",\"type\":\"string\",\"count\":0,\"scripted\":false,\"searchable\":true,\"aggregatable\":true,\"readFromDocValues\":true},{\"name\":\"assignee_uuid\",\"type\":\"string\",\"count\":0,\"scripted\":false,\"searchable\":true,\"aggregatable\":true,\"readFromDocValues\":true},{\"name\":\"author\",\"type\":\"string\",\"count\":0,\"scripted\":false,\"searchable\":true,\"aggregatable\":true,\"readFromDocValues\":true},{\"name\":\"author_bot\",\"type\":\"boolean\",\"count\":0,\"scripted\":false,\"searchable\":true,\"aggregatable\":true,\"readFromDocValues\":true},{\"name\":\"author_domain\",\"type\":\"string\",\"count\":0,\"scripted\":false,\"searchable\":true,\"aggregatable\":true,\"readFromDocValues\":true},{\"name\":\"author_gender\",\"type\":\"string\",\"count\":0,\"scripted\":false,\"searchable\":true,\"aggregatable\":true,\"readFromDocValues\":true},{\"name\":\"author_gender_acc\",\"type\":\"number\",\"count\":0,\"scripted\":false,\"searchable\":true,\"aggregatable\":true,\"readFromDocValues\":true},{\"name\":\"author_id\",\"type\":\"string\",\"count\":0,\"scripted\":false,\"searchable\":true,\"aggregatable\":true,\"readFromDocValues\":true},{\"name\":\"author_login\",\"type\":\"string\",\"count\":0,\"scripted\":false,\"searchable\":true,\"aggregatable\":true,\"readFromDocValues\":true},{\"name\":\"author_name\",\"type\":\"string\",\"count\":0,\"scripted\":false,\"searchable\":true,\"aggregatable\":true,\"readFromDocValues\":true},{\"name\":\"author_org_name\",\"type\":\"string\",\"count\":0,\"scripted\":false,\"searchable\":true,\"aggregatable\":true,\"readFromDocValues\":true},{\"name\":\"author_type\",\"type\":\"string\",\"count\":0,\"scripted\":false,\"searchable\":true,\"aggregatable\":true,\"readFromDocValues\":true},{\"name\":\"author_tz\",\"type\":\"string\",\"count\":0,\"scripted\":false,\"searchable\":true,\"aggregatable\":true,\"readFromDocValues\":true},{\"name\":\"author_user_name\",\"type\":\"string\",\"count\":0,\"scripted\":false,\"searchable\":true,\"aggregatable\":true,\"readFromDocValues\":true},{\"name\":\"author_uuid\",\"type\":\"string\",\"count\":0,\"scripted\":false,\"searchable\":true,\"aggregatable\":true,\"readFromDocValues\":true},{\"name\":\"body\",\"type\":\"string\",\"count\":0,\"scripted\":false,\"searchable\":true,\"aggregatable\":false,\"readFromDocValues\":false},{\"name\":\"changes\",\"type\":\"number\",\"count\":0,\"scripted\":false,\"searchable\":true,\"aggregatable\":true,\"readFromDocValues\":true},{\"name\":\"comment_id\",\"type\":\"string\",\"count\":0,\"scripted\":false,\"searchable\":true,\"aggregatable\":true,\"readFromDocValues\":true},{\"name\":\"created\",\"type\":\"date\",\"count\":0,\"scripted\":false,\"searchable\":true,\"aggregatable\":true,\"readFromDocValues\":true},{\"name\":\"creation_date\",\"type\":\"date\",\"count\":0,\"scripted\":false,\"searchable\":true,\"aggregatable\":true,\"readFromDocValues\":true},{\"name\":\"creator_bot\",\"type\":\"boolean\",\"count\":0,\"scripted\":false,\"searchable\":true,\"aggregatable\":true,\"readFromDocValues\":true},{\"name\":\"creator_domain\",\"type\":\"string\",\"count\":0,\"scripted\":false,\"searchable\":true,\"aggregatable\":true,\"readFromDocValues\":true},{\"name\":\"creator_gender\",\"type\":\"string\",\"count\":0,\"scripted\":false,\"searchable\":true,\"aggregatable\":true,\"readFromDocValues\":true},{\"name\":\"creator_gender_acc\",\"type\":\"number\",\"count\":0,\"scripted\":false,\"searchable\":true,\"aggregatable\":true,\"readFromDocValues\":true},{\"name\":\"creator_id\",\"type\":\"string\",\"count\":0,\"scripted\":false,\"searchable\":true,\"aggregatable\":true,\"readFromDocValues\":true},{\"name\":\"creator_login\",\"type\":\"string\",\"count\":0,\"scripted\":false,\"searchable\":true,\"aggregatable\":true,\"readFromDocValues\":true},{\"name\":\"creator_name\",\"type\":\"string\",\"count\":0,\"scripted\":false,\"searchable\":true,\"aggregatable\":true,\"readFromDocValues\":true},{\"name\":\"creator_org_name\",\"type\":\"string\",\"count\":0,\"scripted\":false,\"searchable\":true,\"aggregatable\":true,\"readFromDocValues\":true},{\"name\":\"creator_tz\",\"type\":\"string\",\"count\":0,\"scripted\":false,\"searchable\":true,\"aggregatable\":true,\"readFromDocValues\":true},{\"name\":\"creator_user_name\",\"type\":\"string\",\"count\":0,\"scripted\":false,\"searchable\":true,\"aggregatable\":true,\"readFromDocValues\":true},{\"name\":\"creator_uuid\",\"type\":\"string\",\"count\":0,\"scripted\":false,\"searchable\":true,\"aggregatable\":true,\"readFromDocValues\":true},{\"name\":\"grimoire_creation_date\",\"type\":\"date\",\"count\":0,\"scripted\":false,\"searchable\":true,\"aggregatable\":true,\"readFromDocValues\":true},{\"name\":\"id\",\"type\":\"string\",\"count\":0,\"scripted\":false,\"searchable\":true,\"aggregatable\":true,\"readFromDocValues\":true},{\"name\":\"is_jira_comment\",\"type\":\"number\",\"count\":0,\"scripted\":false,\"searchable\":true,\"aggregatable\":true,\"readFromDocValues\":true},{\"name\":\"is_jira_issue\",\"type\":\"number\",\"count\":0,\"scripted\":false,\"searchable\":true,\"aggregatable\":true,\"readFromDocValues\":true},{\"name\":\"issue_description\",\"type\":\"string\",\"count\":0,\"scripted\":false,\"searchable\":true,\"aggregatable\":true,\"readFromDocValues\":true},{\"name\":\"issue_key\",\"type\":\"string\",\"count\":0,\"scripted\":false,\"searchable\":true,\"aggregatable\":true,\"readFromDocValues\":true},{\"name\":\"issue_type\",\"type\":\"string\",\"count\":0,\"scripted\":false,\"searchable\":true,\"aggregatable\":true,\"readFromDocValues\":true},{\"name\":\"issue_url\",\"type\":\"string\",\"count\":0,\"scripted\":false,\"searchable\":true,\"aggregatable\":true,\"readFromDocValues\":true},{\"name\":\"key\",\"type\":\"string\",\"count\":0,\"scripted\":false,\"searchable\":true,\"aggregatable\":true,\"readFromDocValues\":true},{\"name\":\"labels\",\"type\":\"string\",\"count\":0,\"scripted\":false,\"searchable\":true,\"aggregatable\":true,\"readFromDocValues\":true},{\"name\":\"main_description\",\"type\":\"string\",\"count\":0,\"scripted\":false,\"searchable\":true,\"aggregatable\":true,\"readFromDocValues\":true},{\"name\":\"main_description_analyzed\",\"type\":\"string\",\"count\":0,\"scripted\":false,\"searchable\":true,\"aggregatable\":false,\"readFromDocValues\":false},{\"name\":\"metadata__enriched_on\",\"type\":\"date\",\"count\":0,\"scripted\":false,\"searchable\":true,\"aggregatable\":true,\"readFromDocValues\":true},{\"name\":\"metadata__gelk_backend_name\",\"type\":\"string\",\"count\":0,\"scripted\":false,\"searchable\":true,\"aggregatable\":true,\"readFromDocValues\":true},{\"name\":\"metadata__gelk_version\",\"type\":\"string\",\"count\":0,\"scripted\":false,\"searchable\":true,\"aggregatable\":true,\"readFromDocValues\":true},{\"name\":\"metadata__timestamp\",\"type\":\"date\",\"count\":0,\"scripted\":false,\"searchable\":true,\"aggregatable\":true,\"readFromDocValues\":true},{\"name\":\"metadata__updated_on\",\"type\":\"date\",\"count\":0,\"scripted\":false,\"searchable\":true,\"aggregatable\":true,\"readFromDocValues\":true},{\"name\":\"number_of_comments\",\"type\":\"number\",\"count\":0,\"scripted\":false,\"searchable\":true,\"aggregatable\":true,\"readFromDocValues\":true},{\"name\":\"origin\",\"type\":\"string\",\"count\":0,\"scripted\":false,\"searchable\":true,\"aggregatable\":true,\"readFromDocValues\":true},{\"name\":\"original_time_estimation\",\"type\":\"number\",\"count\":0,\"scripted\":false,\"searchable\":true,\"aggregatable\":true,\"readFromDocValues\":true},{\"name\":\"original_time_estimation_hours\",\"type\":\"number\",\"count\":0,\"scripted\":false,\"searchable\":true,\"aggregatable\":true,\"readFromDocValues\":true},{\"name\":\"priority\",\"type\":\"string\",\"count\":0,\"scripted\":false,\"searchable\":true,\"aggregatable\":true,\"readFromDocValues\":true},{\"name\":\"progress_total\",\"type\":\"number\",\"count\":0,\"scripted\":false,\"searchable\":true,\"aggregatable\":true,\"readFromDocValues\":true},{\"name\":\"project\",\"type\":\"string\",\"count\":0,\"scripted\":false,\"searchable\":true,\"aggregatable\":true,\"readFromDocValues\":true},{\"name\":\"project_1\",\"type\":\"string\",\"count\":0,\"scripted\":false,\"searchable\":true,\"aggregatable\":true,\"readFromDocValues\":true},{\"name\":\"project_id\",\"type\":\"string\",\"count\":0,\"scripted\":false,\"searchable\":true,\"aggregatable\":true,\"readFromDocValues\":true},{\"name\":\"project_key\",\"type\":\"string\",\"count\":0,\"scripted\":false,\"searchable\":true,\"aggregatable\":true,\"readFromDocValues\":true},{\"name\":\"project_name\",\"type\":\"string\",\"count\":0,\"scripted\":false,\"searchable\":true,\"aggregatable\":true,\"readFromDocValues\":true},{\"name\":\"releases\",\"type\":\"string\",\"count\":0,\"scripted\":false,\"searchable\":true,\"aggregatable\":true,\"readFromDocValues\":true},{\"name\":\"reporter_bot\",\"type\":\"boolean\",\"count\":0,\"scripted\":false,\"searchable\":true,\"aggregatable\":true,\"readFromDocValues\":true},{\"name\":\"reporter_domain\",\"type\":\"string\",\"count\":0,\"scripted\":false,\"searchable\":true,\"aggregatable\":true,\"readFromDocValues\":true},{\"name\":\"reporter_gender\",\"type\":\"string\",\"count\":0,\"scripted\":false,\"searchable\":true,\"aggregatable\":true,\"readFromDocValues\":true},{\"name\":\"reporter_gender_acc\",\"type\":\"number\",\"count\":0,\"scripted\":false,\"searchable\":true,\"aggregatable\":true,\"readFromDocValues\":true},{\"name\":\"reporter_id\",\"type\":\"string\",\"count\":0,\"scripted\":false,\"searchable\":true,\"aggregatable\":true,\"readFromDocValues\":true},{\"name\":\"reporter_login\",\"type\":\"string\",\"count\":0,\"scripted\":false,\"searchable\":true,\"aggregatable\":true,\"readFromDocValues\":true},{\"name\":\"reporter_name\",\"type\":\"string\",\"count\":0,\"scripted\":false,\"searchable\":true,\"aggregatable\":true,\"readFromDocValues\":true},{\"name\":\"reporter_org_name\",\"type\":\"string\",\"count\":0,\"scripted\":false,\"searchable\":true,\"aggregatable\":true,\"readFromDocValues\":true},{\"name\":\"reporter_tz\",\"type\":\"string\",\"count\":0,\"scripted\":false,\"searchable\":true,\"aggregatable\":true,\"readFromDocValues\":true},{\"name\":\"reporter_user_name\",\"type\":\"string\",\"count\":0,\"scripted\":false,\"searchable\":true,\"aggregatable\":true,\"readFromDocValues\":true},{\"name\":\"reporter_uuid\",\"type\":\"string\",\"count\":0,\"scripted\":false,\"searchable\":true,\"aggregatable\":true,\"readFromDocValues\":true},{\"name\":\"resolution_date\",\"type\":\"date\",\"count\":0,\"scripted\":false,\"searchable\":true,\"aggregatable\":true,\"readFromDocValues\":true},{\"name\":\"resolution_description\",\"type\":\"string\",\"count\":0,\"scripted\":false,\"searchable\":true,\"aggregatable\":true,\"readFromDocValues\":true},{\"name\":\"resolution_id\",\"type\":\"string\",\"count\":0,\"scripted\":false,\"searchable\":true,\"aggregatable\":true,\"readFromDocValues\":true},{\"name\":\"resolution_name\",\"type\":\"string\",\"count\":0,\"scripted\":false,\"searchable\":true,\"aggregatable\":true,\"readFromDocValues\":true},{\"name\":\"resolution_self\",\"type\":\"string\",\"count\":0,\"scripted\":false,\"searchable\":true,\"aggregatable\":true,\"readFromDocValues\":true},{\"name\":\"status\",\"type\":\"string\",\"count\":0,\"scripted\":false,\"searchable\":true,\"aggregatable\":true,\"readFromDocValues\":true},{\"name\":\"status_description\",\"type\":\"string\",\"count\":0,\"scripted\":false,\"searchable\":true,\"aggregatable\":true,\"readFromDocValues\":true},{\"name\":\"summary\",\"type\":\"string\",\"count\":0,\"scripted\":false,\"searchable\":true,\"aggregatable\":true,\"readFromDocValues\":true},{\"name\":\"tag\",\"type\":\"string\",\"count\":0,\"scripted\":false,\"searchable\":true,\"aggregatable\":true,\"readFromDocValues\":true},{\"name\":\"time_estimation\",\"type\":\"number\",\"count\":0,\"scripted\":false,\"searchable\":true,\"aggregatable\":true,\"readFromDocValues\":true},{\"name\":\"time_estimation_hours\",\"type\":\"number\",\"count\":0,\"scripted\":false,\"searchable\":true,\"aggregatable\":true,\"readFromDocValues\":true},{\"name\":\"time_spent\",\"type\":\"number\",\"count\":0,\"scripted\":false,\"searchable\":true,\"aggregatable\":true,\"readFromDocValues\":true},{\"name\":\"time_spent_hours\",\"type\":\"number\",\"count\":0,\"scripted\":false,\"searchable\":true,\"aggregatable\":true,\"readFromDocValues\":true},{\"name\":\"time_to_close_days\",\"type\":\"number\",\"count\":0,\"scripted\":false,\"searchable\":true,\"aggregatable\":true,\"readFromDocValues\":true},{\"name\":\"time_to_last_update_days\",\"type\":\"number\",\"count\":0,\"scripted\":false,\"searchable\":true,\"aggregatable\":true,\"readFromDocValues\":true},{\"name\":\"type\",\"type\":\"string\",\"count\":0,\"scripted\":false,\"searchable\":true,\"aggregatable\":true,\"readFromDocValues\":true},{\"name\":\"updateAuthor\",\"type\":\"string\",\"count\":0,\"scripted\":false,\"searchable\":true,\"aggregatable\":true,\"readFromDocValues\":true},{\"name\":\"updateAuthor_bot\",\"type\":\"boolean\",\"count\":0,\"scripted\":false,\"searchable\":true,\"aggregatable\":true,\"readFromDocValues\":true},{\"name\":\"updateAuthor_domain\",\"type\":\"string\",\"count\":0,\"scripted\":false,\"searchable\":true,\"aggregatable\":true,\"readFromDocValues\":true},{\"name\":\"updateAuthor_gender\",\"type\":\"string\",\"count\":0,\"scripted\":false,\"searchable\":true,\"aggregatable\":true,\"readFromDocValues\":true},{\"name\":\"updateAuthor_gender_acc\",\"type\":\"number\",\"count\":0,\"scripted\":false,\"searchable\":true,\"aggregatable\":true,\"readFromDocValues\":true},{\"name\":\"updateAuthor_id\",\"type\":\"string\",\"count\":0,\"scripted\":false,\"searchable\":true,\"aggregatable\":true,\"readFromDocValues\":true},{\"name\":\"updateAuthor_name\",\"type\":\"string\",\"count\":0,\"scripted\":false,\"searchable\":true,\"aggregatable\":true,\"readFromDocValues\":true},{\"name\":\"updateAuthor_org_name\",\"type\":\"string\",\"count\":0,\"scripted\":false,\"searchable\":true,\"aggregatable\":true,\"readFromDocValues\":true},{\"name\":\"updateAuthor_tz\",\"type\":\"string\",\"count\":0,\"scripted\":false,\"searchable\":true,\"aggregatable\":true,\"readFromDocValues\":true},{\"name\":\"updateAuthor_user_name\",\"type\":\"string\",\"count\":0,\"scripted\":false,\"searchable\":true,\"aggregatable\":true,\"readFromDocValues\":true},{\"name\":\"updateAuthor_uuid\",\"type\":\"string\",\"count\":0,\"scripted\":false,\"searchable\":true,\"aggregatable\":true,\"readFromDocValues\":true},{\"name\":\"updated\",\"type\":\"date\",\"count\":0,\"scripted\":false,\"searchable\":true,\"aggregatable\":true,\"readFromDocValues\":true},{\"name\":\"url\",\"type\":\"string\",\"count\":0,\"scripted\":false,\"searchable\":true,\"aggregatable\":true,\"readFromDocValues\":true},{\"name\":\"uuid\",\"type\":\"string\",\"count\":0,\"scripted\":false,\"searchable\":true,\"aggregatable\":true,\"readFromDocValues\":true},{\"name\":\"watchers\",\"type\":\"number\",\"count\":0,\"scripted\":false,\"searchable\":true,\"aggregatable\":true,\"readFromDocValues\":true},{\"name\":\"painless_delay\",\"type\":\"number\",\"count\":0,\"scripted\":true,\"script\":\"List resolution_statuses = new ArrayList();\\nresolution_statuses.add('Closed');\\nresolution_statuses.add('Done');\\n\\ndouble now = Duration.between(LocalDateTime.ofInstant(Instant.ofEpochMilli(doc['grimoire_creation_date'].value.millis), ZoneId.of('Z')), LocalDateTime.ofInstant(Instant.ofEpochMilli(new Date().getTime()), ZoneId.of('Z'))).toMinutes()/1440.0;\\n\\ndouble resolution_date = Duration.between(LocalDateTime.ofInstant(Instant.ofEpochMilli(doc['grimoire_creation_date'].value.millis), ZoneId.of('Z')), LocalDateTime.ofInstant(Instant.ofEpochMilli(doc['resolution_date'].value.millis), ZoneId.of('Z'))).toMinutes()/1440.0;\\n\\nif (doc.containsKey('status') && doc.containsKey('is_closed') && doc['is_closed'].value == 1) {\\n  if (doc.containsKey('resolution_date') && doc['resolution_date'].size() != 0 && resolution_statuses.contains(doc['status'].value)) {\\n    return resolution_date;\\n  }\\n  return doc['time_to_close_days'].value;\\n}\\nreturn now;\",\"lang\":\"painless\",\"searchable\":true,\"aggregatable\":true,\"readFromDocValues\":false}]",
                "release_date": "2020-08-04T16:00:10.501508",
                "timeFieldName": "resolution_date",
                "title": "jira_resolution_date"
            }
        }
    ]
}